domain_events/__init__.py
domain_events/event.py
domain_events/publisher.py
domain_events/subscriber.py
domain_events-2.2.0.dist-info/licenses/LICENSE
domain_events-2.2.0.dist-info/METADATA
domain_events-2.2.0.dist-info/WHEEL
domain_events-2.2.0.dist-info/top_level.txt
domain_events-2.2.0.dist-info/RECORD
