Metadata-Version: 2.4
Name: domain-events
Version: 2.2.0
Summary: A lightweight library with an implementation of Pub-Sub.
Home-page: https://github.com/agroptima/domain-events
Download-URL: https://github.com/agroptima/domain-events/releases
Author: Isagri S.L.U.
Author-email: devs.es@groupeisagri.com
License: GPLv3
Keywords: python,ddd
Classifier: Development Status :: 5 - Production/Stable
Classifier: Intended Audience :: Developers
Classifier: License :: OSI Approved :: GNU General Public License v3 (GPLv3)
Classifier: Natural Language :: English
Classifier: Operating System :: OS Independent
Classifier: Programming Language :: Python
Classifier: Topic :: Utilities
License-File: LICENSE
Requires-Dist: pytz
Dynamic: author
Dynamic: author-email
Dynamic: classifier
Dynamic: description
Dynamic: description-content-type
Dynamic: download-url
Dynamic: home-page
Dynamic: keywords
Dynamic: license
Dynamic: license-file
Dynamic: requires-dist
Dynamic: summary
